streamlit_json_tip/__init__.py
streamlit_json_tip/frontend/package-lock.json
streamlit_json_tip/frontend/package.json
streamlit_json_tip/frontend/build/asset-manifest.json
streamlit_json_tip/frontend/build/index.html
streamlit_json_tip/frontend/build/static/css/main.618c2b16.css
streamlit_json_tip/frontend/build/static/css/main.618c2b16.css.map
streamlit_json_tip/frontend/build/static/js/main.96bf47b4.js
streamlit_json_tip/frontend/build/static/js/main.96bf47b4.js.LICENSE.txt
streamlit_json_tip/frontend/build/static/js/main.96bf47b4.js.map
streamlit_json_tip/frontend/public/index.html
streamlit_json_tip/frontend/src/JsonViewer.css
streamlit_json_tip/frontend/src/JsonViewer.js
streamlit_json_tip/frontend/src/JsonViewer.test.js
streamlit_json_tip/frontend/src/index.js
streamlit_json_tip/frontend/src/setupTests.js
streamlit_json_tip-0.2.8.dist-info/licenses/LICENSE
tests/__init__.py
tests/test_json_viewer.py
streamlit_json_tip-0.2.8.dist-info/METADATA
streamlit_json_tip-0.2.8.dist-info/WHEEL
streamlit_json_tip-0.2.8.dist-info/top_level.txt
streamlit_json_tip-0.2.8.dist-info/RECORD
