Metadata-Version: 2.4
Name: streamlit-json-tip
Version: 0.2.8
Summary: A Streamlit custom component for viewing JSON with interactive tooltips and tags
Home-page: https://github.com/yourusername/streamlit-json-tip
Author: Your Name
Author-email: Isaac <isaac@example.com>
License: MIT
Project-URL: Homepage, https://github.com/isaac/streamlit-json-tip
Project-URL: Documentation, https://github.com/isaac/streamlit-json-tip#readme
Project-URL: Repository, https://github.com/isaac/streamlit-json-tip
Project-URL: Bug Tracker, https://github.com/isaac/streamlit-json-tip/issues
Keywords: streamlit,json,viewer,tooltip,component,interactive
Classifier: Development Status :: 4 - Beta
Classifier: Intended Audience :: Developers
Classifier: Topic :: Software Development :: Libraries :: Python Modules
Classifier: Topic :: Scientific/Engineering :: Visualization
Classifier: Topic :: Scientific/Engineering :: Information Analysis
Classifier: Programming Language :: Python :: 3
Classifier: Programming Language :: Python :: 3.8
Classifier: Programming Language :: Python :: 3.9
Classifier: Programming Language :: Python :: 3.10
Classifier: Programming Language :: Python :: 3.11
Classifier: Programming Language :: Python :: 3.12
Classifier: License :: OSI Approved :: MIT License
Classifier: Operating System :: OS Independent
Requires-Python: >=3.6
License-File: LICENSE
Requires-Dist: streamlit>=1.0.0
Dynamic: author
Dynamic: home-page
Dynamic: license-file
Dynamic: requires-python
